crystaldb/__init__.py
crystaldb/compat.py
crystaldb/config.py
crystaldb/db.py
crystaldb/exception.py
crystaldb/utils.py
crystaldb-1.1.2.dist-info/LICENSE
crystaldb-1.1.2.dist-info/METADATA
crystaldb-1.1.2.dist-info/WHEEL
crystaldb-1.1.2.dist-info/top_level.txt
crystaldb-1.1.2.dist-info/RECORD
