Metadata-Version: 2.1
Name: crystaldb
Version: 1.1.2
Summary: CrystalDB is a simple and small ORM and  no need to provide a model.
Home-page: https://github.com/fuzctc/crystaldb.py.git
Author: Zhichang Fu
Author-email: fuzctc@gmail.com
License: UNKNOWN
Platform: UNKNOWN
Requires: mysqlclient
Requires: DBUtils
Requires-Dist: mysqlclient
Requires-Dist: DBUtils
